lokilogger/__init__.py
lokilogger/config.ini
lokilogger/logging.py
lokilogger-1.0.3.dist-info/WHEEL
lokilogger-1.0.3.dist-info/METADATA
lokilogger-1.0.3.dist-info/RECORD
