Metadata-Version: 2.1
Name: lokilogger
Version: 1.0.3
Summary: This a custom `logging` for `Loki`
Home-page: https://github.com/polynom-company/lokilogger
Author: kangyili
Requires-Python: >=3.8,<4.0
Classifier: Programming Language :: Python :: 3
Classifier: Programming Language :: Python :: 3.8
Classifier: Programming Language :: Python :: 3.9
Requires-Dist: colorlog (>=6.6.0,<7.0.0)
Project-URL: Repository, https://github.com/polynom-company/lokilogger
